ffpack/__init__.py
ffpack/__main__.py
ffpack/config.py
ffpack/fdm/__init__.py
ffpack/fdm/minerModel.py
ffpack/lcc/__init__.py
ffpack/lcc/astmCounting.py
ffpack/lcc/fourPointCounting.py
ffpack/lcc/johannessonCounting.py
ffpack/lcc/meanStressCorrection.py
ffpack/lcc/rychlikCounting.py
ffpack/lsg/__init__.py
ffpack/lsg/autoregressiveMovingAverage.py
ffpack/lsg/randomWalk.py
ffpack/lsg/sequenceFromSpectrum.py
ffpack/lsm/__init__.py
ffpack/lsm/cycleCountingMatrix.py
ffpack/lsm/sequenceSpectra.py
ffpack/lsm/waveSpectra.py
ffpack/lsm/windSpectra.py
ffpack/rpm/__init__.py
ffpack/rpm/metropolisHastings.py
ffpack/rpm/nataf.py
ffpack/rrm/__init__.py
ffpack/rrm/firstOrderReliabilityMethod.py
ffpack/rrm/firstOrderSecondMoment.py
ffpack/rrm/secondOrderReliabilityMethod.py
ffpack/rrm/simulationBasedReliabilityMethod.py
ffpack/utils/__init__.py
ffpack/utils/aggregation.py
ffpack/utils/countingMatrix.py
ffpack/utils/derivatives.py
ffpack/utils/digitization.py
ffpack/utils/fitter.py
ffpack/utils/sequenceFilter.py
ffpack-0.3.3.dist-info/LICENSE
ffpack-0.3.3.dist-info/METADATA
ffpack-0.3.3.dist-info/WHEEL
ffpack-0.3.3.dist-info/RECORD
