Metadata-Version: 2.1
Name: ffpack
Version: 0.3.3
Summary: Fatigue and fracture package
Home-page: https://pypi.org/project/ffpack
Keywords: fatigue,fracture,load,reliability
Author: Dongping Zhu
Maintainer: Dongping Zhu
Requires-Python: >=3.7,<3.12
Classifier: License :: OSI Approved :: GNU General Public License v3 (GPLv3)
Classifier: Programming Language :: Python
Classifier: Programming Language :: Python :: 3
Classifier: Programming Language :: Python :: 3.7
Classifier: Programming Language :: Python :: 3.8
Classifier: Programming Language :: Python :: 3.9
Classifier: Programming Language :: Python :: 3.10
Classifier: Programming Language :: Python :: 3.11
Classifier: Topic :: Scientific/Engineering
Requires-Dist: scipy (>=1.2,<1.8) ; python_version == "3.7"
Requires-Dist: scipy (>=1.8,<2.0) ; python_version >= "3.8" and python_version < "3.11"
Project-URL: Documentation, https://ffpack.readthedocs.io/en/latest/
Project-URL: Repository, https://github.com/dpzhuX/ffpack
